aharp/__init__.py
aharp/__main__.py
aharp/cli.py
aharp/session.py
aharp/tabletalk.py
aharp-0.0.1.dist-info/licenses/LICENSE
aharp-0.0.1.dist-info/METADATA
aharp-0.0.1.dist-info/WHEEL
aharp-0.0.1.dist-info/top_level.txt
aharp-0.0.1.dist-info/RECORD
