Metadata-Version: 2.4
Name: aharp
Version: 0.0.1
Summary: AHARP (Analytics & History Auto-Report Printer): a free, offline toolkit for multi-dataset exploration, exportable reports, time-series analysis, rich plotting, and fuzzy-matched NLP queries.
Author-email: rishasur <4.lossy.subnets@icloud.com>
License-Expression: MIT
Requires-Python: >=3.8
License-File: LICENSE
Requires-Dist: pandas>=1.1.0
Requires-Dist: numpy>=1.21.0
Requires-Dist: scikit-learn>=1.0.0
Requires-Dist: matplotlib>=3.0.0
Requires-Dist: rapidfuzz>=2.0.0
Requires-Dist: markdown>=3.0.0
Dynamic: license-file
